{
  "$schema": "http://json-schema.org/draft-04/schema#",

  "title": "REST API get caps/l3ca",
  "description": "GET Pool L3 CAT caps result, URI /caps/l3ca",

  "type": "object",

  "properties": {
    "cache_size": {
      "description": "L3 cache size",
      "type": "integer"
    },
    "cw_size": {
      "description": "L3 cache way size",
      "type": "integer"
    },
    "cw_num": {
      "description": "A number of L3 cache ways",
      "type": "integer"
    },
    "clos_num": {
      "description": "A number of supported classes of service",
      "type": "integer"
    },
    "cdp_supported": {
      "description": "L3 CDP support",
      "type": "boolean"
    },
    "cdp_enabled": {
      "description": "L3 CDP status (enabled/disabled)",
      "type": "boolean"
    }
  },
  "required": ["cache_size", "cw_size", "cw_num", "clos_num", "cdp_supported", "cdp_enabled"],
  "additionalProperties": false
}
